eintf/__init__.py
eintf/common/__init__.py
eintf/common/helper.py
eintf/db/__init__.py
eintf/db/db.py
eintf/extractor/__init__.py
eintf/extractor/git.py
eintf/extractor/huds_megalist.py
eintf/extractor/map/__init__.py
eintf/extractor/map/map_crawler.py
eintf/extractor/news/__init__.py
eintf/extractor/news/etf_crawler.py
eintf/extractor/news/news.py
eintf/extractor/news/rgl_crawler.py
eintf/extractor/news/ugc_crawler.py
eintf/main.py
eintf-0.0.7.dist-info/METADATA
eintf-0.0.7.dist-info/WHEEL
eintf-0.0.7.dist-info/entry_points.txt
eintf-0.0.7.dist-info/RECORD
