Metadata-Version: 2.1
Name: eintf
Version: 0.0.7
Summary: 
Author: kshib
Author-email: ksyko@pm.me
Requires-Python: >=3.9,<4.0
Classifier: Programming Language :: Python :: 3
Classifier: Programming Language :: Python :: 3.9
Classifier: Programming Language :: Python :: 3.10
Classifier: Programming Language :: Python :: 3.11
Requires-Dist: bs4 (>=0.0.1,<0.0.2)
Requires-Dist: fastapi (>=0.91.0,<0.92.0)
Requires-Dist: minify-html (>=0.10.8,<0.11.0)
Requires-Dist: pymongo (>=4.3.3,<5.0.0)
Requires-Dist: requests (>=2.28.1,<3.0.0)
Requires-Dist: scrapy (>=2.7.1,<3.0.0)
Requires-Dist: uvicorn (>=0.20.0,<0.21.0)
